macpy/__init__.py
macpy/constant/EC.py
macpy/constant/VK.py
macpy/constant/XK/3270.py
macpy/constant/XK/APL.py
macpy/constant/XK/ARABIC.py
macpy/constant/XK/ARMENIAN.py
macpy/constant/XK/BRAILLE.py
macpy/constant/XK/CAUCASUS.py
macpy/constant/XK/CURRENCY.py
macpy/constant/XK/CYRILLIC.py
macpy/constant/XK/GEORGIAN.py
macpy/constant/XK/GREEK.py
macpy/constant/XK/HEBREW.py
macpy/constant/XK/KATAKANA.py
macpy/constant/XK/KOREAN.py
macpy/constant/XK/LATIN1.py
macpy/constant/XK/LATIN2.py
macpy/constant/XK/LATIN3.py
macpy/constant/XK/LATIN4.py
macpy/constant/XK/LATIN8.py
macpy/constant/XK/LATIN9.py
macpy/constant/XK/MATHEMATICAL.py
macpy/constant/XK/MISCELLANY.py
macpy/constant/XK/PUBLISHING.py
macpy/constant/XK/SINHALA.py
macpy/constant/XK/SPECIAL.py
macpy/constant/XK/TECHNICAL.py
macpy/constant/XK/THAI.py
macpy/constant/XK/VIETNAMESE.py
macpy/constant/XK/XF86.py
macpy/constant/XK/XKB_KEYS.py
macpy/constant/XK/__init__.py
macpy/constant/__init__.py
macpy/constant/windows.py
macpy/constant/xatom.py
macpy/constant/xmap.py
macpy/event.py
macpy/interface/__init__.py
macpy/interface/evkeyboard.py
macpy/interface/evpointer.py
macpy/interface/winkeyboard.py
macpy/interface/winpointer.py
macpy/interface/winwindow.py
macpy/interface/xhelper.py
macpy/interface/xkeyboard.py
macpy/interface/xpointer.py
macpy/interface/xwindow.py
macpy/key.py
macpy/libxkbswitch/__init__.py
macpy/libxkbswitch/libxkbswitch.x86.so
macpy/libxkbswitch/libxkbswitch.x86_64.so
macpy/platform.py
macpy/types/__init__.py
macpy/types/dummy.py
macpy/types/metawindow.py
macpy/types/structures.py
macpy/types/tuples.py
macpy/types/undefenum.py
macpy/version.py
macpy-0.1.3.dist-info/WHEEL
macpy-0.1.3.dist-info/METADATA
macpy-0.1.3.dist-info/RECORD
