Metadata-Version: 2.1
Name: macpy
Version: 0.1.3
Summary: Simple, cross-platform macros/GUI automation for python
Home-page: https://github.com/OzymandiasTheGreat/macpy
License: LGPL-3.0-or-later
Author: Ozymandias
Author-email: tomas.rav@gmail.com
Requires-Python: >=3.6,<4.0
Classifier: Development Status :: 4 - Beta
Classifier: Environment :: Win32 (MS Windows)
Classifier: Environment :: X11 Applications
Classifier: Intended Audience :: Developers
Classifier: License :: OSI Approved :: GNU Lesser General Public License v3 or later (LGPLv3+)
Classifier: Operating System :: Microsoft :: Windows
Classifier: Operating System :: POSIX :: Linux
Classifier: Programming Language :: Python :: 3
Classifier: Programming Language :: Python :: 3.6
Classifier: Programming Language :: Python :: 3.7
Classifier: Programming Language :: Python :: 3.8
Classifier: Programming Language :: Python :: 3.9
Requires-Dist: evdev (>=1.3.0,<2.0.0); sys_platform == "linux"
Requires-Dist: python-libinput (>=0.1.0,<0.2.0); sys_platform == "linux"
Requires-Dist: python-xlib (>=0.26,<0.27); sys_platform == "linux"
Project-URL: Repository, https://github.com/OzymandiasTheGreat/macpy
